README.rst
setup.py
TaliffDB/__init__.py
TaliffDB/client.py
TaliffDB/server.py
TaliffDB.egg-info/PKG-INFO
TaliffDB.egg-info/SOURCES.txt
TaliffDB.egg-info/dependency_links.txt
TaliffDB.egg-info/requires.txt
TaliffDB.egg-info/top_level.txt