Metadata-Version: 1.0
Name: TaliffDB
Version: 0.2
Summary: A server for python3 sqlite3
Home-page: https://github.com/Mcilie/TaliffDB/
Author: Michael Ilie
Author-email: mcilie@icloud.com
License: MIT
Platform: UNKNOWN
